stackhut_client-0.1.1.dist-info/pbr.json
stackhut_client-0.1.1.dist-info/metadata.json
stackhut_client-0.1.1.dist-info/top_level.txt
stackhut_client-0.1.1.dist-info/RECORD
stackhut_client-0.1.1.dist-info/WHEEL
stackhut_client-0.1.1.dist-info/DESCRIPTION.rst
stackhut_client-0.1.1.dist-info/METADATA
stackhut_client/__init__.py
stackhut_client/client.py
