Metadata-Version: 2.0
Name: stackhut-client
Version: 0.1.1
Summary: StackHut client-side Python library
Home-page: https://github.com/stackhut/client-python
Author: StackHut
Author-email: client@stackhut.com
License: Apache
Keywords: stackhut
Platform: POSIX
Classifier: Development Status :: 2 - Pre-Alpha
Classifier: Intended Audience :: Developers
Classifier: Environment :: Console
Classifier: Natural Language :: English
Classifier: License :: OSI Approved :: Apache Software License
Classifier: Operating System :: OS Independent
Classifier: Programming Language :: Python
Classifier: Programming Language :: Python :: 3
Classifier: Programming Language :: Python :: 3.4
Classifier: Topic :: Software Development
Requires-Dist: requests
